package_test/__init__.py
package_test/main.py
my_demo_test_hijackliang-2021.10.15.dist-info/METADATA
my_demo_test_hijackliang-2021.10.15.dist-info/WHEEL
my_demo_test_hijackliang-2021.10.15.dist-info/top_level.txt
my_demo_test_hijackliang-2021.10.15.dist-info/RECORD
