Metadata-Version: 2.1
Name: my-demo-test-hijackliang
Version: 2021.10.15
Summary: A demo for python packaging.
Home-page: https://github.com/mamabi/demo
Author: hijackliang
Author-email: 2858744808@qq.com
License: MIT
Keywords: demo
Platform: UNKNOWN
